cathedral_rl/__init__.py
cathedral_rl/cathedral_v0.py
cathedral_rl/examples/play.py
cathedral_rl/game/board.py
cathedral_rl/game/cathedral.py
cathedral_rl/game/manual_policy.py
cathedral_rl/game/piece.py
cathedral_rl/game/pieces.py
cathedral_rl/game/utils.py
cathedral_rl-1.1.0.dist-info/LICENSE
cathedral_rl-1.1.0.dist-info/WHEEL
cathedral_rl-1.1.0.dist-info/METADATA
cathedral_rl-1.1.0.dist-info/RECORD
